MANIFEST.in
README.md
setup.py
smtp2go_django/__init__.py
smtp2go_django/email_backend.py
smtp2go_django.egg-info/PKG-INFO
smtp2go_django.egg-info/SOURCES.txt
smtp2go_django.egg-info/dependency_links.txt
smtp2go_django.egg-info/not-zip-safe
smtp2go_django.egg-info/requires.txt
smtp2go_django.egg-info/top_level.txt