Metadata-Version: 1.1
Name: smtp2go-django
Version: 2.0.0
Summary: Library for interacting with the SMTP2Go API via Django.
Home-page: https://github.com/smtp2go-oss/smtp2go-django
Author: SMTP2Go
Author-email: devs@smtp2go.com
License: MIT
Platform: UNKNOWN
Classifier: Development Status :: 5 - Production/Stable
Classifier: Intended Audience :: Developers
Classifier: License :: OSI Approved :: MIT License
Classifier: Programming Language :: Python :: 2.7
Classifier: Programming Language :: Python :: 3
Classifier: Topic :: Communications :: Email
Classifier: Topic :: Software Development :: Libraries :: Python Modules
